datapreprep
