Metadata-Version: 1.1
Name: datapreprep
Version: 0.0.3
Summary: A Data Pre Processing Package
Home-page: https://share.streamlit.io/mohammed-muzzammil/data_pre_processing/main/st1.py
Author: Mohammed Muzzammil
Author-email: muzzammilsilat56@gmail.com
License: MIT
Keywords: data processing
Platform: UNKNOWN
Classifier: Development Status :: 5 - Production/Stable
Classifier: Intended Audience :: Education
Classifier: Operating System :: Microsoft :: Windows :: Windows 10
Classifier: License :: OSI Approved :: MIT License
Classifier: Programming Language :: Python :: 3
